[
  {"id": 1, "joke": "😂 Wahd rajel dkhel doktour, gal lih: 'docteur, kolchi lli kanmess kayderni!' Galih doktour: 'la tmess walo!'"},
  {"id": 2, "joke": "😂 Ustadh s2al telmidh: 'chkoun lli ktchef Amrica?' Gal: 'Colomb!' Gal ustad: 'wach konti kayen nta?'"},
  {"id": 3, "joke": "😂 Lwalid gal lwaldo: 'ach bghiti tkoun?' Gal: 'pilot!' Gal lwalid: 'zwina, daba sir dir devoirs dyal lard!'"},
  {"id": 4, "joke": "😂 Wahd dkhel café, gal garçon: '3tini qahwa bla sukkar!' Gal garçon: 'bla sukkar ma3ndnach, walakin 3ndna bla hlib!'"},
  {"id": 5, "joke": "😂 Doktour gal mrid: 'khassek takhod had dwa 3 mrrat f nhar!' Gal mrid: 'wakha, walakin ana ma3ndich gher 2 yidin!'"},
  {"id": 6, "joke": "😂 Telmidh gal ustad: 'ma fhemtch!' Gal ustad: 'chnou?' Gal telmidh: 'kolchi!'"},
  {"id": 7, "joke": "😂 Wahd rajel mcha l bank: '3tini flous!' Gal caissier: '3ndek compte?' Gal: 'iyeh, 3ndi compte bla flous!'"},
  {"id": 8, "joke": "😂 Lwalid gal lwaldo: '3tik flous dyal lekoul?' Gal: 'iyeh!' Gal: 'wach kolti?' Gal: 'la, kont gha nchof menu!'"},
  {"id": 9, "joke": "😂 Wahd s2al jorah: 'wach kayn chi mochkila f rassi?' Gal jorah: 'iyeh, nta lli fiha!'"},
  {"id": 10, "joke": "😂 Rajel gal doktour: 'ana kanfort walakin ma kannamch!' Gal doktour: 'wakha, sir nfort f bitek!'"},
  {"id": 11, "joke": "😂 Telmidh makatabch exam. Gal ustad: 'chnou dert?' Gal: 'mochkila f stylo!' Gal ustad: '3 sa3at w ma ktbti walo?!' Gal: 'nsi3 stylo dyal shi7 bezzaf!'"},
  {"id": 12, "joke": "😂 Wahd gal s7aboh: '3raft nmchi b tomobile mn 3 snin!' Gal s7aboh: 'mazal ma 3refti tkherej mn garage?'"},
  {"id": 13, "joke": "😂 Doktour gal mrid: '3ndek chi allergy?' Gal mrid: 'iyeh, 3ndi allergy mn khedma!'"},
  {"id": 14, "joke": "😂 Wahd mcha yshri tomobile jdida. Gal ba3: 'ma3ndihach 7ta mochkila!' Mn ba3d semana: 'galti ma3ndihach mochkila, lyoum ma bedat!'"},
  {"id": 15, "joke": "😂 Rajel gal mratoh: 'kul nhar kantfkker fiki!' Galat: '3lach?' Gal: 'hit ma3ndi walo khour ndeer!'"},
  {"id": 16, "joke": "😂 Wahd mcha l hammam, mn ba3d sa3a rja3. Galat mratoh: 'wach 3eytilech?' Gal: 'kan nstenna tqouli tji!'"},
  {"id": 17, "joke": "😂 Telmidh kateb f exam: 'Allah a3lem!' Gal ustad: '20/20 l Allah, 0 lik nta!'"},
  {"id": 18, "joke": "😂 Wahd gal s7aboh: 'kayn chi far f dari!' Gal: 'sir jibi chat!' Gal: 'chat ma ymchi 3la far, ymshi 3la wifi!'"},
  {"id": 19, "joke": "😂 Doktour gal mrid: 'lazem tnajem bzzaf!' Gal mrid: 'w ana lli 3andi 6 wlad, wach hada machi bzzaf?'"},
  {"id": 20, "joke": "😂 Ustad s2al: 'chkoun lli khtera2 telephone?' Gal: 'Graham Bell!' Gal ustad: 'wach kant 3endoh mra?' Gal: 'hit ma kan fiha wi-fi, kant threb!'"},
  {"id": 21, "joke": "😂 Wahd mcha yshri khobz, rja3 bla khobz. Galat mratoh: 'fin lkhobz?' Gal: 'ma kaynch!' Galat: '9olthlek tshri!' Gal: 'iyeh, walakin ma kaynch!'"},
  {"id": 22, "joke": "😂 Mra galat rajlha: 'shrit robe jdida!' Gal: 'ghalia bezzaf!' Galat: 'la, taman dyal 3 robe!' Gal: 'w 3endna chi taman dyal 3 robe f dari?'"},
  {"id": 23, "joke": "😂 Wahd gal: 'ana ghadi nbda diet mn ghda!' S7aboh: 'hit mn ghda?' Gal: 'hit lyoum kayna pizza!'"},
  {"id": 24, "joke": "😂 Telmidh gal ustad: 'wach y9der 2+2 ykoun 5?' Gal ustad: 'la!' Gal: 'tayach 3la calculator diyali!'"},
  {"id": 25, "joke": "😂 Wahd gal: 'kanensa kolchi mn ba3d 5 d9ay9!' Gal s7aboh: '9e3ed hna, ghadi nrja3 lik mn ba3d 5 d9ay9!'"},
  {"id": 26, "joke": "😂 Doktour gal: 'wach katkhdem sport?' Gal mrid: 'iyeh! kana3tadel zrabi kol nhar!'"},
  {"id": 27, "joke": "😂 Wahd gal: '3ndi fikra 3zhima!' Gal s7aboh: '9ol liya!' Gal: 'nsitiha!'"},
  {"id": 28, "joke": "😂 Mra galat: 'rajli kaytfker dima f shghel!' Galat jaritiha: 'mzyan!' Galat: 'la, kaytfker fih w ma kaykhdemch!'"},
  {"id": 29, "joke": "😂 Wahd dkhel restaurant: 'wach kayn chi haja bla tomato? 3ndi allergy!' Gal garçon: 'kayna lmaya!' Gal: 'w bla lmaya?'"},
  {"id": 30, "joke": "😂 Ustad s2al: 'chnou howo l volcano?' Gal telmidh: 'jbal lli b7al bik ustad, ila z3et, ykhrej dakhkhan!'"},
  {"id": 31, "joke": "😂 Wahd s2al f interview: 'wach 3endek experience?' Gal: 'iyeh, 10 snin f b7th 3la khedma!'"},
  {"id": 32, "joke": "😂 Rajel gal l doktour: 'mrati ma katkellemniich!' Gal doktour: 'hada machi mochkila, hada baraka!'"},
  {"id": 33, "joke": "😂 Wahd gal: '3ndi 3 degrees!' S7aboh: '3lach ma khdemtich?' Gal: 'ma 3endich experience!'"},
  {"id": 34, "joke": "😂 Telmidh ma jabch note zwin. Gal lwalid: 'chnou had note?' Gal telmidh: 'ustadhi b7al biya!'"},
  {"id": 35, "joke": "😂 Wahd gal: '3ndi moyen special nwaqef tomobili!' S7aboh: 'chnou?' Gal: 'mankheddemhach!'"},
  {"id": 36, "joke": "😂 Doktour gal: 'ma tkolch sukkar!' Gal mrid: 'wach ma nkolch cake? la. chocolat? la. glace? la.' Gal: 'docteur, w nta kifach 3ayesh?'"},
  {"id": 37, "joke": "😂 Wahd gal jiranoh: '3ndek chi flous?' Gal: 'gha bach n3ref wach ana wa7id lli ma 3endich!'"},
  {"id": 38, "joke": "😂 Ustad s2al: 'chnou hiya l joghrafiya?' Gal telmidh: 'l 3ilm lli kaykhelli l ustad y9ra min lmaghreb l canada!'"},
  {"id": 39, "joke": "😂 Wahd gal: '3ndi programme dyal sport kol nhar, kan7mel remote w kanshof match!'"},
  {"id": 40, "joke": "😂 Rajel gal s7aboh: 'mrati bkat lbara7 hit galitha nti mzyana f sha9a dyal jirtiha!'"},
  {"id": 41, "joke": "😂 Wahd gal: 'ana mazelt kanhdem f proyet mn 3 snin!' S7aboh: 'chnou proyet?' Gal: 'nkhrrj mn ddar!'"},
  {"id": 42, "joke": "😂 Mra galat: 'rajli kaykheddem bla waqfa!' Galat jaritiha: 'mzyan!' Galat: 'la, 3endou magasin lhajra f dari!'"},
  {"id": 43, "joke": "😂 Wahd shaf affiche chef cuisinier experience 5 ans. Gal s7aboh: 'n9dem! 3ndi 20 3am d experience f makla!'"},
  {"id": 44, "joke": "😂 Telmidh 9ra kol lil. Gal ustad: '9ol liya wach howa lma?' Gal: 'H2O!' Gal: 'w l 3adhab?' Gal: 'nsi bssif!'"},
  {"id": 45, "joke": "😂 Wahd 9bel interview gal: 'rabbi 3wenni!' Mn ba3d gal: 'rabbi makensma3kch hit nsi lik!'"},
  {"id": 46, "joke": "😂 Doktour gal: '3endek tension!' Gal mrid: 'normal, 3endi 4 wlad w kra f Casablanca!'"},
  {"id": 47, "joke": "😂 Wahd gal: 'ana ghadi ndir diet b suhula! kol l7wajat lli ma 3endich!'"},
  {"id": 48, "joke": "😂 Ustad s2al: 'chnou howa l thermometre?' Gal telmidh: 'chi haja lli tikhroj m3a dema f lbled kol sa3a!'"},
  {"id": 49, "joke": "😂 Wahd gal: 'sme3t sot ghriba f darek lbara7!' Gal jiran: 'iyeh, kont nchouf match w m3ah 7zina!'"},
  {"id": 50, "joke": "😂 Mra galat: '3ndi chi joie lyoum, rajli msha safar w khella liya remote!'"},
  {"id": 51, "joke": "😂 Wahd gal s7aboh: '3erraft nkheddem b 2 yidin f waqt wahd, f telephone w f makla!'"},
  {"id": 52, "joke": "😂 Telmidh kteb f exam: 'la hada la hada!' Gal ustad: '9olliya s7i7!' Gal: 'hada!'"},
  {"id": 53, "joke": "😂 Wahd gal: '3ndi tomobile fast bezzaf! kol ma nshghelha, police katrked warraya!'"},
  {"id": 54, "joke": "😂 Rajel gal mratoh: 'bghit ndir regime!' Galat: 'mzyan! bda mn daba!' Gal: 'la, mn ba3d l3sha!'"},
  {"id": 55, "joke": "😂 Wahd gal: '9rit 7etta l aakhir!' S7aboh: 'wach fhemti?' Gal: 'la, walakin 9rit!'"},
  {"id": 56, "joke": "😂 Ustad s2al: 'chnou howo l Nil?' Gal telmidh: 'nhar kbir f Egypte... w fi lmaghrib kayna oued!'"},
  {"id": 57, "joke": "😂 Wahd gal: '3ndi 3 degrees!' S7aboh: 'bravo!' Gal: 'iyeh, walakin 3andi 0 khedma!'"},
  {"id": 58, "joke": "😂 Mra galat rajlha: 'ghadi nkhrej m3a s7abiyat!' Gal: 'wakha!' Galat: 'w 3endek flous?' Gal: 'rje3i zwin!'"},
  {"id": 59, "joke": "😂 Wahd dkhel l banque: 'bghit ndir compte!' Gal caissier: 'wach 3endek flous?' Gal: 'la, hit jit l hna bach njibb!'"},
  {"id": 60, "joke": "😂 Doktour s2al: '9addach 3endek 3mer?' Gal mrid: '45, w 3ayesh 3la wladi!'"},
  {"id": 61, "joke": "😂 Telmidh gal ustad: 'ana kankum bssif f dars dyalek!'"},
  {"id": 62, "joke": "😂 Wahd gal: 'ana ghadi nmchi l Canada!' S7aboh: 'chnou ghadi tdeer temma?' Gal: 'ghadi nchouf wach kayn l7al!'"},
  {"id": 63, "joke": "😂 Rajel gal l mekhayyat: 'Allah dar l 3alam f 7 iyyam, w nta kat9olliya pantalon f semana?'"},
  {"id": 64, "joke": "😂 Wahd gal s7aboh: 'bghit nlha! l7ya kbira bezzaf, 3eyya nshofha fl miroir!'"},
  {"id": 65, "joke": "😂 Doktour gal mrid: 'lazem triyyed fumo!' Gal mrid: 'mat3arrafnich 3la chi haja jdida docteur!'"},
  {"id": 66, "joke": "😂 Wahd mcha yshri perfume l mratoh: 'bghiti wahd lli ma tezhersh hta mn ba3d nhar!'"},
  {"id": 67, "joke": "😂 Telmidh gal ustad: '9rit 100 saf7a lbara7!' Gal ustad: 'bravo! f ach ktab?' Gal: 'menu d restaurant!'"},
  {"id": 68, "joke": "😂 Wahd gal: 'kol nhar kanqra f bibliotheque, kayna wifi!'"},
  {"id": 69, "joke": "😂 Ustad s2al: 'chnou howo l atome?' Gal telmidh: 'chi haja lli ila tkessret, dert mochkila kbira!'"},
  {"id": 70, "joke": "😂 Wahd dkhel hanout: 'bghit shi haja b 10 drhm!' Gal ba3: '10 drhm? khud hwa!'"},
  {"id": 71, "joke": "😂 Wahd gal: 'ana 3erraft nkoun silent!' S7aboh: 'chnou galti?'"},
  {"id": 72, "joke": "😂 Mra galat l doktour: '3ndi 3 wlad w bghit nwled mra khra!' Gal doktour: 'w rajlek?' Galat: 'huwa lli gal liya n9ollak!'"},
  {"id": 73, "joke": "😂 Wahd gal s7aboh: '3erraft nkheddem télé bla remote! ghadi w rajel, w ghadi w rajel!'"},
  {"id": 74, "joke": "😂 Telmidh gal ustad: 'kont 3yyan lbara7!' Gal ustad: 'wach mshiti docteur?' Gal: 'la, mshit l exam!'"},
  {"id": 75, "joke": "😂 Wahd gal: 'bghit nkoun millionnaire b 40 3am! ghadi nkheddem bezzaf hada 3am!'"},
  {"id": 76, "joke": "😂 Doktour gal: 'lazem tkhod had dwa b lma!' Gal mrid: 'wach ma y9derch b cola?'"},
  {"id": 77, "joke": "😂 Wahd gal jiranoh: 'wach tomobilik jdida?' Gal: 'iyeh!' Gal: '7it ma 3endich garage, wach nkhellsek f nafs lprix?'"},
  {"id": 78, "joke": "😂 Rajel gal mratoh: 'ana kanfer, bla ghda, bla l3sha, bla walo!'"},
  {"id": 79, "joke": "😂 Wahd gal s7aboh: '3ndi feeling ana lli ghadi nkoun president! ma khdem khedma walo w mazal 3ayesh mzyan!'"},
  {"id": 80, "joke": "😂 Ustad s2al: 'chnou hiya capital dyal Japan?' Gal telmidh: 'J!' Gal ustad: '3afak?!' Gal: 'ustadh, gal liya 9el awwel letre!'"},
  {"id": 81, "joke": "😂 Wahd gal l doktour: 'kantfkker bezzaf f mochkilat lli ma 3endich!'"},
  {"id": 82, "joke": "😂 Mra galat rajlha: 'bghit nshri ach ma kan!' Gal: 'w ana bghit 3ndi ach makench!'"},
  {"id": 83, "joke": "😂 Wahd gal: '9rit kol ktab f libraria! kol titres!'"},
  {"id": 84, "joke": "😂 Telmidh gal ustad: 'kifach nkoun successful?' Gal ustad: 'kdem bezzaf, sir lili!' Gal: 'wach nta derti haka?' Gal ustad: 'la, walakin nasah l3ibad!'"},
  {"id": 85, "joke": "😂 Wahd dkhel hotel: '3tini chambre b view dyal chi haja mzyana, ana ma3endish waqt!'"},
  {"id": 86, "joke": "😂 Doktour gal: 'khassek tariyyed kol haja!' Gal mrid: 'wach khatbi riyyed l 3qel b7al?'"},
  {"id": 87, "joke": "😂 Wahd gal: '3reft nmchi b vélo! mn dar jiri 7etta dar 7mid, velo 9adim bezzaf!'"},
  {"id": 88, "joke": "😂 Ustad s2al: 'chnou hiya l chimie?' Gal telmidh: 'l 3ilm lli 3allemnach l doktour wach ydir b dwa!'"},
  {"id": 89, "joke": "😂 Rajel gal mratoh: 'ana ghadi nsifi!' Galat: 'wach ghadi tji?' Gal: 'ghadi nshof!'"},
  {"id": 90, "joke": "😂 Wahd gal s7aboh: '3ndi fikra, sahel bezzaf, hit ma fiha walo!'"},
  {"id": 91, "joke": "😂 Telmidh gal ustad: 'wach safi l exam? wach kan s7ib?' Gal ustad: 'iyeh, ila konti 9rit!'"},
  {"id": 92, "joke": "😂 Wahd gal: 'kantkhyel dima fi sfera! walakin khyel bezzaf!'"},
  {"id": 93, "joke": "😂 Mra galat: 'rajli 3ando takhtit zwin, ghadi ydir nap mn daba l retirement!'"},
  {"id": 94, "joke": "😂 Wahd gal doktour: 'ana 3ndi headache mn 3 iyyam!' Gal doktour: 'w chnou dert?' Gal: 'walo, nstenna trou7 whedha!'"},
  {"id": 95, "joke": "😂 Ustad s2al: 'chnou howa l barq?' Gal telmidh: 'chi haja lli kat3yyet 3lik ila kherjat l factoura dial lektrona!'"},
  {"id": 96, "joke": "😂 Wahd shrit telephone b 5000 drhm! S7aboh: 'wach dkhel lik?' Gal: 'iyeh, dkhel lik rass dyal douar!'"},
  {"id": 97, "joke": "😂 Rajel gal jiranoh: 'sber 3la musique lbara7!' Gal: 'mzyana bezzaf, walakin kont bghit nnaam!'"},
  {"id": 98, "joke": "😂 Wahd gal: 'kanbqa nqra 7etta s3a 3! hit nsa9 min 3 n7aoul nnaam!'"},
  {"id": 99, "joke": "😂 Doktour gal: 'khassek tdir sport!' Gal mrid: 'mn lili bach ma t3ebch!'"},
  {"id": 100, "joke": "😂 Wahd gal s7aboh: 'ana kayen 3ndi plan!' S7aboh: 'chnou?' Gal: 'ma 3ndi plan!'"},
  {"id": 101, "joke": "😂 Wahd gal l jiranoh: '3endek sel-tape?' Gal: 'iyeh, chnou?' Gal: '3endak jar lli katkellem bezzaf!'"},
  {"id": 102, "joke": "😂 Wahd 9bel ma ynaam: 'rabbi 3tini l flous dyal kra!' Mn ba3d shwiya: 'rabbi, w dyal lekoul b7al!'"},
  {"id": 103, "joke": "😂 Mra galat jaritiha: 'rajli kaykheddem kter mn lazem!' Galat: 'mzyan!' Galat: 'la, kaykhdem f dari w ma kaykhdemch f khedmto!'"},
  {"id": 104, "joke": "😂 Wahd gal: 'ana 3erraft nkoun motivé! kol nhar nsift video motivé... w mnba3d nnam!'"},
  {"id": 105, "joke": "😂 Ustad s2al: 'chnou hiya l histoire?' Gal telmidh: 'l 3ilm lli nta3rfo ach daro nas l 9odama w nkhedbo 3lih f exam!'"},
  {"id": 106, "joke": "😂 Wahd gal s7aboh: '3ndi feeling ana lli ghadi nkoun chef!' S7aboh: '3lach?' Gal: 'hit kolt pizza mn supermarché w galou lahyan!'"},
  {"id": 107, "joke": "😂 Telmidh gal ustad: 'kifach ndir ila nsit nkhtam l exam?' Gal: 'khtam b isemk!' Gal: 'iyeh, walakin nsi ismi!'"},
  {"id": 108, "joke": "😂 Wahd gal: 'ana ghadi nbni dari b ydiya!' S7aboh: 'wach 3endek tajriba?' Gal: 'iyeh, bniit 3icha mn karton lbara7!'"},
  {"id": 109, "joke": "😂 Doktour gal: 'lazem tnamel bzzaf!' Gal mrid: 'hssek docteur, ana ma3ndi waqt!'"},
  {"id": 110, "joke": "😂 Wahd gal jiranoh: 'tomobilik katredd!' Gal: 'na3ref, ana lli kayreddha!'"},
  {"id": 111, "joke": "😂 Mra shrat perfume jdid. Galat rajlha: 'wach mazyan?' Gal: 'iyeh, walakin ma 3endich chi haja lli mazyan aktar w rkhas aktar?'"},
  {"id": 112, "joke": "😂 Wahd gal: 'ana 3raft nkheddem computer!' S7aboh: 'chnou 3lerft?' Gal: 'YouTube w Facebook!'"},
  {"id": 113, "joke": "😂 Rajel gal s7aboh: '3ndi mochkila m3a 3eyali, kaykolou w kaykolou w ma yshb3uch!'"},
  {"id": 114, "joke": "😂 Telmidh gal ustad: 'ana mrid!' Gal ustad: 'wach 3endek doctorat?' Gal: 'la!' Gal ustad: '9ra 7etta tjib doctorat, rak mr mrid!'"},
  {"id": 115, "joke": "😂 Wahd dkhel l 7anout: 'bghit kol haja lli 3endek!' Gal ba3: 'wach 3endek flous?' Gal: 'la!' Gal ba3: 'khud hwa bla!'"},
  {"id": 116, "joke": "😂 Doktour gal: 'lazem tkhaf mn sukkar!' Gal mrid: 'ma khafch mn chi haja, hit sukkar 7lu!'"},
  {"id": 117, "joke": "😂 Wahd gal: '3erraft nkoun motivé, kol nhar nsift video motivé w mnba3d nnam!'"},
  {"id": 118, "joke": "😂 Ustad s2al: 'chnou hiya l physique?' Gal telmidh: 'l 3ilm lli kaykhelli l bac ykon ghaleb 3lik!'"},
  {"id": 119, "joke": "😂 Wahd gal: 'ana ghadi ndir entreprise!' S7aboh: 'chnou?' Gal: 'ghadi nbda ndebber!'"},
  {"id": 120, "joke": "😂 Rajel gal l doktour: 'mrati tkellem whi nayma w kat2dherni bezzaf!'"},
  {"id": 121, "joke": "😂 Wahd gal jiranoh: 'sme3t musique mn 3endek lbara7!' Gal jiran: 'iyeh, kont n3zzef!' Gal: 'wach 3erref t3zzef?' Gal: 'la, walakin kont n7awel!'"},
  {"id": 122, "joke": "😂 Telmidh gal ustad: 'ana 3erraft nkoun patient!' Gal ustad: '9ol liya chnou mektob f sabboura?' Gal: 'ghadi nsaber bach n9rah!'"},
  {"id": 123, "joke": "😂 Wahd gal: '3ndi fikra, ghadi nmchi l gym... n7ad flous w nkhrej!'"},
  {"id": 124, "joke": "😂 Doktour gal: 'wach 3endek chi 7asa bi dou?' Gal mrid: 'iyeh, 7asa bi lhwa mnin kayanfokh l fenster!'"},
  {"id": 125, "joke": "😂 Wahd shaf film horror: 'ma kheftch!' S7aboh: 'wach 3endek sha9a?' Gal: 'la, walakin kheft wana n7ed mn sala f l lil!'"},
  {"id": 126, "joke": "😂 Mra galat: 'rajli kayhder bezzaf! katkellem m3a rasoh w kayrredd!'"},
  {"id": 127, "joke": "😂 Wahd gal s7aboh: '9dit note 19 f exam!' S7aboh: 'bravo!' Gal: 'iyeh, 19 mn 100!'"},
  {"id": 128, "joke": "😂 Ustad s2al: 'chnou hiya l démocratie?' Gal telmidh: 'chi nizam lli fih lkol kat9ol raioh w ba3d ma kaysmawch!'"},
  {"id": 129, "joke": "😂 Wahd gal s7aboh: 'shrit villa!' S7aboh: 'wain?' Gal: 'f PlayStation!'"},
  {"id": 130, "joke": "😂 Telmidh gal ustad: 'kifach ndir makla?' Gal ustad: 'chnou 3aref tdeer?' Gal: 'kankoul!'"},
  {"id": 131, "joke": "😂 Wahd gal: '3ndi plan zwin, ghadi nnaam bach nnsa mochkilati!'"},
  {"id": 132, "joke": "😂 Ustad s2al: 'chnou howa l ecosysteme?' Gal telmidh: 'chi haja lli ila khelliti, tkessret!'"},
  {"id": 133, "joke": "😂 Wahd gal jiranu: 'sme3t musique mn 3endek, kont n3zzef!' Gal: 'wach 3erref?' Gal: 'la, walakin kont n7awel!'"},
  {"id": 134, "joke": "😂 Rajel gal mratoh: 'bghit ndir regime!' Galat: 'bda mn lyoum!' Gal: 'wakha, mn ghda!'"},
  {"id": 135, "joke": "😂 Wahd gal: '3ndi intelligence artificielle! ghadi nkhdem AI bach tkhdem 3liya!'"},
  {"id": 136, "joke": "😂 Ustad s2al: 'chnou howa l gravité?' Gal telmidh: 'chi haja lli kaytkhelli kol haja t7et, ghir lhesab lli kayot3eed!'"},
  {"id": 137, "joke": "😂 Wahd gal: 'ana ghadi n9ra bezzaf hada l 3am, kol haja mektoba f menu dial restaurant!'"},
  {"id": 138, "joke": "😂 Rajel mcha yshri tomobile: '3ndna wahda b 300 000!' Gal: 'wach 3ndek chi wahda b 300?'"},
  {"id": 139, "joke": "😂 Wahd gal: 'ana 3raft ndir kol haja!' Mratoh: 'sir ndi l zbel!' Gal: 'kol haja ma 3daha hadi!'"},
  {"id": 140, "joke": "😂 Doktour gal mrid: 'khassek t9ra bezzaf 3la sihha!' Gal mrid: 'ghadi t3ref 3lach mrid walakin ma ykonch dawa!'"},
  {"id": 141, "joke": "😂 Mra galat rajlha: '3ndek chi felous?' Gal: 'la!' Galat: 'w ana bghit nshri chi haja!' Gal: 'w ana bghit 3ndi chi flous!'"},
  {"id": 142, "joke": "😂 Wahd gal jiranoh: 'sme3t tsawit kbira mn 3endek! chnou dert?' Gal: 'kont npleki champignons!'"},
  {"id": 143, "joke": "😂 Telmidh gal ustad: 'ana 3raft kolchi!' Gal ustad: '9ol liya mektoub f sabboura?' Gal: 'nsi!'"},
  {"id": 144, "joke": "😂 Wahd gal s7aboh: 'ana ghadi ndir sport mn ghda!' S7aboh: 'hit mn ghda?' Gal: 'hit lyoum ma 3ndi sport kit!'"},
  {"id": 145, "joke": "😂 Ustad s2al: 'chnou howa l ADN?' Gal telmidh: 'chi haja lli bha tatbet l7aja, aw tatbet l brra3a!'"},
  {"id": 146, "joke": "😂 Wahd gal doktour: 'ana 3ndi mochkila, kantfkker bezzaf!' Gal doktour: 'hada mzyan!' Gal: 'la, kantfkker f mochkilat lli ma 3endich!'"},
  {"id": 147, "joke": "😂 Mra galat jaritiha: 'rajli kayna 3endou takhtit, ghadi ydir nap mn daba l retirement!'"},
  {"id": 148, "joke": "😂 Wahd gal s7aboh: '3reft nmchi b vélo mn dar jiri 7etta dar 7mid, velo 9adim bezzaf!'"},
  {"id": 149, "joke": "😂 Rajel gal jiranoh: 'wach 3endek chi jardin? kayn fiha chi shjar? mzyan, n9der njellib tomobili!'"},
  {"id": 150, "joke": "😂 Wahd gal s7aboh: 'ana b7al flan, ila ma 7rektich, ma 9dertich!'"},
  {"id": 151, "joke": "😂 Telmidh 9bel exam gal: 'rabbi, 3tini lhemm w l wakila!' Mn ba3d l exam gal: 'rabbi, l wakila whedha kafi!'"},
  {"id": 152, "joke": "😂 Wahd gal: 'ana 9adim nmchi nshri, rja3 bla walo!' Mratoh galat: 'chnou shrit?' Gal: 'experience!'"},
  {"id": 153, "joke": "😂 Doktour gal: 'sir dir tahlil d ddemm!' Gal mrid: '3lach? wach bghiti t3ref ismi?'"},
  {"id": 154, "joke": "😂 Ustad s2al: 'chnou howo l parlement?' Gal telmidh: 'blasa lli fih nas kaytkelmu bezzaf w ma kaydiru walo!'"},
  {"id": 155, "joke": "😂 Wahd gal s7aboh: 'ana 3erraft nkoun diplomatic!' S7aboh: 'kifach?' Gal: 'kol ma z3et, kandam w kanskot!'"},
  {"id": 156, "joke": "😂 Mra galat rajlha: 'rajli kayna 3endou 9imma f khedma!' Galat jaritiha: 'bravo!' Galat: 'iyeh, 9imma... dyal 3ardi fih!'"},
  {"id": 157, "joke": "😂 Wahd gal: 'ana ghadi nkhdem mn ddar!' S7aboh: 'chnou khedma?' Gal: 'ghadi nchouf Netlix w n9ol ana working from home!'"},
  {"id": 158, "joke": "😂 Telmidh gal ustad: 'ustadh, ana 3ndi memory kbira!' Gal ustad: '9ol liya chnou dert lbara7!' Gal: 'nsi!'"},
  {"id": 159, "joke": "😂 Wahd gal doktour: 'ana 3ndi 2 mochkilat!' Gal doktour: '9ol liya!' Gal: 'l ula, kanensa kolchi!' Gal doktour: 'w tania?' Gal: 'nsi!'"},
  {"id": 160, "joke": "😂 Ustad s2al: 'chnou hiya l informatique?' Gal telmidh: 'l 3ilm lli bih kaythellaw nas l internet kol nhar!'"},
  {"id": 161, "joke": "😂 Wahd gal s7aboh: 'shrit villa f Marrakech!' S7aboh: 'bravo!' Gal: 'iyeh, f Google Maps!'"},
  {"id": 162, "joke": "😂 Rajel gal mratoh: 'ana 3erraft nkoun saber!' Galat: 'wach sbertti?' Gal: 'iyeh, sabbert 3la mochkilti kol nhar!'"},
  {"id": 163, "joke": "😂 Wahd gal: 'ana ghadi nkoun njem!' S7aboh: 'f ach?' Gal: 'f niyya!'"},
  {"id": 164, "joke": "😂 Telmidh gal ustad: 'ustadh, ana bghit nkoun engineer!' Gal ustad: '3afak, kol liya wach 3 + 5?' Gal: '... calculator ndiru?'"},
  {"id": 165, "joke": "😂 Wahd gal jiranoh: 'sme3t 9ura3 kbira mn darek!' Gal: 'ah, rak 9rit l factura dyal lma!'"},
  {"id": 166, "joke": "😂 Mra galat: 'rajli kaykheddem kol nhar 7etta l lil!' Galat jaritiha: 'mzyan!' Galat: 'la, hit kaykheddem f dar jirtiha!'"},
  {"id": 167, "joke": "😂 Doktour gal mrid: 'ila ma bedlitich 3adatek, ma 3endik gher 3 shhor!' Gal mrid: 'wakha, ghadi nbdelhom mn ba3d 3 shhor!'"},
  {"id": 168, "joke": "😂 Wahd gal: 'ana 3raft nkheddem telephone f lil bla dwa!' S7aboh: 'kifach?' Gal: 'kansedd 3yniya!'"},
  {"id": 169, "joke": "😂 Ustad s2al: 'chnou howo l budget?' Gal telmidh: 'flous lli kayn f niyya w machi f jib!'"},
  {"id": 170, "joke": "😂 Wahd gal s7aboh: 'ana 3reft ndir saving!' S7aboh: 'bravo, 9addach?' Gal: '5 drhm kol shhar!'"},
  {"id": 171, "joke": "😂 Rajel gal mratoh: 'ana ghadi nsifi l casablanca!' Galat: 'wach ghadi tji?' Gal: 'ghadi nshof wach kayna khedma!'"},
  {"id": 172, "joke": "😂 Wahd gal: 'ana 3erraft nkun za3im!' S7aboh: '3lach?' Gal: 'hit 3erraft nhder bezzaf w ma nkhdemch!'"},
  {"id": 173, "joke": "😂 Telmidh gal ustad: 'ustadh, ana 3ndi talent!' Gal ustad: '9ol liya chnou!' Gal: 'talent f nessyan!'"},
  {"id": 174, "joke": "😂 Wahd gal doktour: 'docteur, ana ma kannamch!' Gal doktour: 'wach katfker bezzaf?' Gal: 'la, walakin ma 3ndi matrass!'"},
  {"id": 175, "joke": "😂 Ustad s2al: 'chnou hiya l politique?' Gal telmidh: 'fen kol chi kaytkellem 3la lhaq w ba3d ma kaydiroch!'"},
  {"id": 176, "joke": "😂 Wahd gal s7aboh: 'ana 3reft nmchi b pied l khedma!' S7aboh: 'zwina!' Gal: 'iyeh, walakin tomobile dyal liran 9damt!'"},
  {"id": 177, "joke": "😂 Mra galat jaritiha: 'rajli 3ando 9imma f shghel!' Galat: 'wach mzyan?' Galat: 'iyeh, 9imma... 3la rasso!'"},
  {"id": 178, "joke": "😂 Wahd gal: 'ana 3erraft nkoun optimiste!' S7aboh: 'wach dert?' Gal: 'kol nhar kan9ol: ghda ghadi ykoun mzyan!'"},
  {"id": 179, "joke": "😂 Telmidh gal ustad: 'ustadh, ana 3reft kol haja!' Gal ustad: 'wakha, 9ol liya chnou howa l hawa?' Gal: 'chi haja lli ila ma kanetsh, ma konnasch hna!'"},
  {"id": 180, "joke": "😂 Wahd gal jiranoh: '3endek chi korda?' Gal: 'iyeh chnou?' Gal: 'bghit n3lle9 photo dyal bitek!'"},
  {"id": 181, "joke": "😂 Doktour gal: '3endek chi allergy mn l 3mel?' Gal mrid: 'iyeh, 7it 3emri ma khdemtch w mazal bkhir!'"},
  {"id": 182, "joke": "😂 Wahd gal s7aboh: 'ana 3erraft nkoun strict m3a rassi!' S7aboh: 'wach dert?' Gal: 'mne3t rassi mn kol haja... walakin rja3t!'"},
  {"id": 183, "joke": "😂 Ustad s2al: 'chnou howa l micro-onde?' Gal telmidh: 'chi haja lli kaykhelli mama tat9ol: makla jat!'"},
  {"id": 184, "joke": "😂 Wahd gal: 'ana 3raft ntsena!' S7aboh: 'wach dert?' Gal: 'tsennit 3la order mn Amazon mn 3 snin!'"},
  {"id": 185, "joke": "😂 Rajel gal mratoh: 'ana kanfer!' Galat: 'chnou katfer?' Gal: 'kanfer ghir bach n3ref fin wdert flous!'"},
  {"id": 186, "joke": "😂 Wahd gal s7aboh: 'ana ghadi nbda nqra!' S7aboh: 'wach ghadi t9ra?' Gal: 'comments dyal Instagram!'"},
  {"id": 187, "joke": "😂 Telmidh 9bel exam gal: 'rabbi 3tini lhemm!' Mn ba3d gal: 'rabbi, kont kan9sd lhemm l 9raya, machi lhemm dyal lhesab!'"},
  {"id": 188, "joke": "😂 Wahd gal doktour: 'ana 3ndi mochkila f wzen!' Gal doktour: '3endek overweight!' Gal: 'la docteur, underweight dyal l flous!'"},
  {"id": 189, "joke": "😂 Ustad s2al: 'chnou hiya l sosyolojiya?' Gal telmidh: 'l 3ilm lli kaydrus liras dyal nas!'"},
  {"id": 190, "joke": "😂 Wahd gal s7aboh: 'ana 3erraft nkoun mstaqel!' S7aboh: 'bravo!' Gal: 'iyeh, mstaqel mn khedma, mn kra, mn kolchi!'"},
  {"id": 191, "joke": "😂 Mra galat jaritiha: 'rajli bda ydir sport!' Galat: 'mzyan!' Galat: 'iyeh, sport dyal massage!'"},
  {"id": 192, "joke": "😂 Wahd gal: 'ana koll nhar kanmchi l job!' S7aboh: '3endek khedma?' Gal: 'la, walakin kanmchi n9ra l offres!'"},
  {"id": 193, "joke": "😂 Telmidh gal ustad: 'ustadh, kifach ndir bach nkoun 3aref bkolchi?' Gal ustad: '9ra bezzaf!' Gal: 'wach nta 9rit bezzaf?' Gal ustad: 'la, walakin nasah l3ibad!'"},
  {"id": 194, "joke": "😂 Wahd gal jiranoh: 'wach tomobilek kayna fiha problème?' Gal: 'la, ghir ma katkheddemch!'"},
  {"id": 195, "joke": "😂 Doktour gal mrid: 'lazem tshreb bezzaf dyal lma!' Gal mrid: 'wach ma y9derch café?'"},
  {"id": 196, "joke": "😂 Wahd gal: 'ana 3erraft nkoun entrepreneur!' S7aboh: 'chnou project?' Gal: 'ghadi nbi3 lhwa... bl 3efya!'"},
  {"id": 197, "joke": "😂 Ustad s2al: 'chnou hiya l philosophie?' Gal telmidh: 'l 3ilm lli bih t9der tsali jodour bla ma tjaweb!'"},
  {"id": 198, "joke": "😂 Wahd gal s7aboh: 'ana 3erraft nkoun min lmutafawwiqin!' S7aboh: 'fach?' Gal: 'f nessyan l mochkilat!'"},
  {"id": 199, "joke": "😂 Rajel gal mratoh: 'ana ghadi ndir nap!' Galat: '9addach?' Gal: 'hetta ma t9olilich ya3ni ghda!'"},
  {"id": 200, "joke": "😂 Wahd gal jiranoh: 'fhmit l 7yat!' Gal jiran: 'chnou fhemti?' Gal: 'walo, walakin fhmit lli ma kayn ma ifhem!"}
]
